[
  {
    "id": "gi_new_001",
    "text": "What does the \"equal protection of the law\" clause guarantee?",
    "options": [
      {
        "id": "a",
        "text": "All citizens will be treated exactly the same under the law."
      },
      {
        "id": "b",
        "text": "Certain groups may be treated differently under the law."
      },
      {
        "id": "c",
        "text": "Only the wealthy will receive legal protection."
      },
      {
        "id": "d",
        "text": "The law is not applicable to all citizens."
      }
    ],
    "correctAnswer": "a",
    "explanation": "",
    "category": "General Information",
    "difficulty": "medium",
    "language": "en"
  },
  {
    "id": "gi_new_002",
    "text": "What is the primary role of the Commission on Human Rights?",
    "options": [
      {
        "id": "a",
        "text": "Investigating crimes"
      },
      {
        "id": "b",
        "text": "Protecting the rights of individuals against abuses by the government"
      },
      {
        "id": "c",
        "text": "Enforcing labor laws"
      },
      {
        "id": "d",
        "text": "Overseeing environmental protection"
      }
    ],
    "correctAnswer": "b",
    "explanation": "",
    "category": "General Information",
    "difficulty": "medium",
    "language": "en"
  },
  {
    "id": "gi_new_003",
    "text": "The following are limitations on freedom of speech, EXCEPT:",
    "options": [
      {
        "id": "a",
        "text": "speech that incites to violence"
      },
      {
        "id": "b",
        "text": "speech that defames a person"
      },
      {
        "id": "c",
        "text": "speech that is critical of the government"
      },
      {
        "id": "d",
        "text": "speech that is false and malicious"
      }
    ],
    "correctAnswer": "c",
    "explanation": "",
    "category": "General Information",
    "difficulty": "medium",
    "language": "en"
  },
  {
    "id": "gi_new_004",
    "text": "The following are powers of the President EXCEPT:",
    "options": [
      {
        "id": "a",
        "text": "to veto legislation"
      },
      {
        "id": "b",
        "text": "to appoint members of the Cabinet"
      },
      {
        "id": "c",
        "text": "to declare martial law"
      },
      {
        "id": "d",
        "text": "to create new provinces"
      }
    ],
    "correctAnswer": "d",
    "explanation": "",
    "category": "General Information",
    "difficulty": "medium",
    "language": "en"
  },
  {
    "id": "gi_new_005",
    "text": "The following are rights of citizens EXCEPT:",
    "options": [
      {
        "id": "a",
        "text": "the right to life, liberty, and property"
      },
      {
        "id": "b",
        "text": "the right to free speech"
      },
      {
        "id": "c",
        "text": "the right to bear arms"
      },
      {
        "id": "d",
        "text": "the right to be free from unreasonable searches and seizures"
      }
    ],
    "correctAnswer": "c",
    "explanation": "Not explicitly guaranteed in the Philippine Constitution",
    "category": "General Information",
    "difficulty": "medium",
    "language": "en"
  },
  {
    "id": "gi_new_006",
    "text": "The following are fundamental duties of citizens EXCEPT:",
    "options": [
      {
        "id": "a",
        "text": "to obey the laws of the land"
      },
      {
        "id": "b",
        "text": "to defend the Constitution"
      },
      {
        "id": "c",
        "text": "to serve the country"
      },
      {
        "id": "d",
        "text": "to pay taxes"
      }
    ],
    "correctAnswer": "c",
    "explanation": "Not a constitutional duty per se — defense of the State is, but \"serve the country\" is vague",
    "category": "General Information",
    "difficulty": "medium",
    "language": "en"
  },
  {
    "id": "gi_new_007",
    "text": "Annie responded to a letter within 15 working days. What duty is she performing?",
    "options": [
      {
        "id": "a",
        "text": "act immediately on the public's personal transactions"
      },
      {
        "id": "b",
        "text": "act promptly on letters and requests"
      },
      {
        "id": "c",
        "text": "make documents accessible to the public"
      },
      {
        "id": "d",
        "text": "submit annual performance reports"
      }
    ],
    "correctAnswer": "b",
    "explanation": "",
    "category": "General Information",
    "difficulty": "medium",
    "language": "en"
  },
  {
    "id": "gi_new_008",
    "text": "Jam rendered a performance report within 45 working days after year-end. What duty is she performing?",
    "options": [
      {
        "id": "a",
        "text": "act immediately on personal transactions"
      },
      {
        "id": "b",
        "text": "act promptly on letters"
      },
      {
        "id": "c",
        "text": "make documents accessible"
      },
      {
        "id": "d",
        "text": "submit annual performance reports"
      }
    ],
    "correctAnswer": "d",
    "explanation": "",
    "category": "General Information",
    "difficulty": "medium",
    "language": "en"
  },
  {
    "id": "gi_new_009",
    "text": "Nekko processed documents with not more than 3 signatories. What duty is he performing?",
    "options": [
      {
        "id": "a",
        "text": "act immediately on personal transactions"
      },
      {
        "id": "b",
        "text": "act promptly on letters"
      },
      {
        "id": "c",
        "text": "make documents accessible"
      },
      {
        "id": "d",
        "text": "submit annual performance reports"
      }
    ],
    "correctAnswer": "e",
    "explanation": "",
    "category": "General Information",
    "difficulty": "medium",
    "language": "en"
  },
  {
    "id": "gi_new_010",
    "text": "Fe attends to anyone who wants to avail of HLURB services promptly. What duty is she performing?",
    "options": [
      {
        "id": "a",
        "text": "act immediately on the public's personal transactions"
      },
      {
        "id": "b",
        "text": "act promptly on letters"
      },
      {
        "id": "c",
        "text": "make documents accessible"
      },
      {
        "id": "d",
        "text": "submit annual performance reports"
      }
    ],
    "correctAnswer": "a",
    "explanation": "",
    "category": "General Information",
    "difficulty": "medium",
    "language": "en"
  },
  {
    "id": "gi_new_011",
    "text": "Marie makes all public documents accessible to the public within reasonable working hours. What duty?",
    "options": [
      {
        "id": "a",
        "text": "act immediately on personal transactions"
      },
      {
        "id": "b",
        "text": "act promptly on letters"
      },
      {
        "id": "c",
        "text": "make documents accessible to the public"
      },
      {
        "id": "d",
        "text": "submit annual performance reports"
      }
    ],
    "correctAnswer": "c",
    "explanation": "",
    "category": "General Information",
    "difficulty": "medium",
    "language": "en"
  },
  {
    "id": "gi_new_012",
    "text": "The following constitute prohibited acts EXCEPT:",
    "options": [
      {
        "id": "a",
        "text": "having financial or material interest in transactions needing approval"
      },
      {
        "id": "b",
        "text": "engaging in private practice of profession unless authorized and won't conflict with official functions"
      },
      {
        "id": "c",
        "text": "recommending any person to any position in a private enterprise with official transaction"
      },
      {
        "id": "d",
        "text": "using confidential information to further private interests"
      }
    ],
    "correctAnswer": "b",
    "explanation": "Option b is actually ALLOWED — private practice is permitted if authorized and doesn't conflict",
    "category": "General Information",
    "difficulty": "medium",
    "language": "en"
  },
  {
    "id": "gi_new_013",
    "text": "When are human rights considered inalienable?",
    "options": [
      {
        "id": "a",
        "text": "When granted by a governing body"
      },
      {
        "id": "b",
        "text": "Only during an individual's lifetime"
      },
      {
        "id": "c",
        "text": "When an individual willingly forfeits them"
      },
      {
        "id": "d",
        "text": "Throughout an individual's existence"
      }
    ],
    "correctAnswer": "d",
    "explanation": "",
    "category": "General Information",
    "difficulty": "medium",
    "language": "en"
  },
  {
    "id": "gi_new_014",
    "text": "What is the purpose of the Universal Declaration of Human Rights?",
    "options": [
      {
        "id": "a",
        "text": "To establish a world government"
      },
      {
        "id": "b",
        "text": "To promote respect for human rights and freedoms"
      },
      {
        "id": "c",
        "text": "To define the responsibilities of member states"
      },
      {
        "id": "d",
        "text": "To enforce international law"
      }
    ],
    "correctAnswer": "b",
    "explanation": "",
    "category": "General Information",
    "difficulty": "medium",
    "language": "en"
  },
  {
    "id": "gi_new_015",
    "text": "What is emphasized as the highest aspiration of the common people?",
    "options": [
      {
        "id": "a",
        "text": "Promotion of social progress"
      },
      {
        "id": "b",
        "text": "Protection of human rights by the rule of law"
      },
      {
        "id": "c",
        "text": "Freedom of speech and belief"
      },
      {
        "id": "d",
        "text": "Development of friendly relations between nations"
      }
    ],
    "correctAnswer": "c",
    "explanation": "",
    "category": "General Information",
    "difficulty": "medium",
    "language": "en"
  },
  {
    "id": "gi_new_016",
    "text": "What is one of the flagship programs of the NTF-ELCAC?",
    "options": [
      {
        "id": "a",
        "text": "Anti-Trafficking Program"
      },
      {
        "id": "b",
        "text": "Barangay Development Program"
      },
      {
        "id": "c",
        "text": "Solo Parents Act"
      },
      {
        "id": "d",
        "text": "Excellence in Education Act"
      }
    ],
    "correctAnswer": "b",
    "explanation": "",
    "category": "General Information",
    "difficulty": "medium",
    "language": "en"
  },
  {
    "id": "gi_new_017",
    "text": "Which law raised the minimum age of sexual consent from 12 to 16 years old?",
    "options": [
      {
        "id": "a",
        "text": "Expanded Anti-Trafficking in Persons Act"
      },
      {
        "id": "b",
        "text": "Foundling Recognition and Protection Act"
      },
      {
        "id": "c",
        "text": "Act providing for stronger protection against rape and sexual exploitation"
      },
      {
        "id": "d",
        "text": "Domestic Administrative Adoption and Alternative Child Care Act"
      }
    ],
    "correctAnswer": "c",
    "explanation": "",
    "category": "General Information",
    "difficulty": "medium",
    "language": "en"
  },
  {
    "id": "gi_new_018",
    "text": "What does Executive Order 163, s. 2022 aim to guarantee?",
    "options": [
      {
        "id": "a",
        "text": "Access to socio-economic services"
      },
      {
        "id": "b",
        "text": "Access to tertiary education"
      },
      {
        "id": "c",
        "text": "Access to government jobs"
      },
      {
        "id": "d",
        "text": "Access to healthcare services"
      }
    ],
    "correctAnswer": "a",
    "explanation": "",
    "category": "General Information",
    "difficulty": "medium",
    "language": "en"
  },
  {
    "id": "gi_new_019",
    "text": "What does Republic Act No. 11650 mandate the establishment of?",
    "options": [
      {
        "id": "a",
        "text": "Learning Resource Center for Learners with Disabilities"
      },
      {
        "id": "b",
        "text": "Teachers Education Centers of Excellence"
      },
      {
        "id": "c",
        "text": "Barangay Development Program"
      },
      {
        "id": "d",
        "text": "National Authority for Child Care"
      }
    ],
    "correctAnswer": "a",
    "explanation": "",
    "category": "General Information",
    "difficulty": "medium",
    "language": "en"
  },
  {
    "id": "gi_new_020",
    "text": "What has the General Assembly proclaimed the UDHR to be?",
    "options": [
      {
        "id": "a",
        "text": "A binding legal document"
      },
      {
        "id": "b",
        "text": "A common standard of achievement for all peoples and nations"
      },
      {
        "id": "c",
        "text": "A set of guidelines for Member States"
      },
      {
        "id": "d",
        "text": "A declaration of war against human rights violations"
      }
    ],
    "correctAnswer": "b",
    "explanation": "",
    "category": "General Information",
    "difficulty": "medium",
    "language": "en"
  },
  {
    "id": "gi_new_021",
    "text": "What is the objective of the progressive measures mentioned in the UDHR Preamble?",
    "options": [
      {
        "id": "a",
        "text": "To eliminate all forms of rebellion"
      },
      {
        "id": "b",
        "text": "To create a world without any conflicts"
      },
      {
        "id": "c",
        "text": "To establish a global government"
      },
      {
        "id": "d",
        "text": "To secure universal and effective recognition and observance of human rights"
      }
    ],
    "correctAnswer": "d",
    "explanation": "",
    "category": "General Information",
    "difficulty": "medium",
    "language": "en"
  },
  {
    "id": "gi_new_022",
    "text": "Who are the intended beneficiaries of the effective recognition of human rights?",
    "options": [
      {
        "id": "a",
        "text": "Only the Member States"
      },
      {
        "id": "b",
        "text": "Only territories under Member States"
      },
      {
        "id": "c",
        "text": "Both peoples of Member States and territories under their jurisdiction"
      },
      {
        "id": "d",
        "text": "Only the General Assembly"
      }
    ],
    "correctAnswer": "c",
    "explanation": "",
    "category": "General Information",
    "difficulty": "medium",
    "language": "en"
  },
  {
    "id": "gi_new_023",
    "text": "In exercising rights and freedoms, individuals are subject to limitations for the purpose of:",
    "options": [
      {
        "id": "a",
        "text": "Ensuring public order"
      },
      {
        "id": "b",
        "text": "Preserving national security"
      },
      {
        "id": "c",
        "text": "Protecting the environment"
      },
      {
        "id": "d",
        "text": "Securing recognition and respect for others' rights"
      }
    ],
    "correctAnswer": "d",
    "explanation": "",
    "category": "General Information",
    "difficulty": "medium",
    "language": "en"
  },
  {
    "id": "gi_new_024",
    "text": "In peacebuilding, what does DDR stand for?",
    "options": [
      {
        "id": "a",
        "text": "Dialogue, Development, and Reconciliation"
      },
      {
        "id": "b",
        "text": "Disarmament, Demobilization, and Reintegration"
      },
      {
        "id": "c",
        "text": "Diplomacy, Democracy, and Reconstruction"
      },
      {
        "id": "d",
        "text": "Diversity, Decentralization, and Redistribution"
      }
    ],
    "correctAnswer": "b",
    "explanation": "",
    "category": "General Information",
    "difficulty": "medium",
    "language": "en"
  },
  {
    "id": "gi_new_025",
    "text": "Which instrument outlines the rights of indigenous peoples including self-determination?",
    "options": [
      {
        "id": "a",
        "text": "Universal Declaration on the Rights of Indigenous Peoples"
      },
      {
        "id": "b",
        "text": "International Labour Organization Convention No. 169"
      },
      {
        "id": "c",
        "text": "Convention on Biological Diversity"
      },
      {
        "id": "d",
        "text": "Rio Declaration on Environment and Development"
      }
    ],
    "correctAnswer": "a",
    "explanation": "",
    "category": "General Information",
    "difficulty": "medium",
    "language": "en"
  },
  {
    "id": "gi_new_026",
    "text": "Which term describes reestablishing social and political stability in a post-conflict society?",
    "options": [
      {
        "id": "a",
        "text": "Humanitarian Intervention"
      },
      {
        "id": "b",
        "text": "Transitional Justice"
      },
      {
        "id": "c",
        "text": "Peacebuilding"
      },
      {
        "id": "d",
        "text": "Conflict Resolution"
      }
    ],
    "correctAnswer": "c",
    "explanation": "",
    "category": "General Information",
    "difficulty": "medium",
    "language": "en"
  },
  {
    "id": "gi_new_027",
    "text": "What is the significance of Executive Order 163, s. 2022?",
    "options": [
      {
        "id": "a",
        "text": "It establishes a program for refugees to gain access to higher education."
      },
      {
        "id": "b",
        "text": "It guarantees the rights of refugees, stateless persons, and asylum seekers to essential services."
      },
      {
        "id": "c",
        "text": "It mandates learning resource centers for learners with disabilities."
      },
      {
        "id": "d",
        "text": "It strengthens government mechanisms to combat human trafficking."
      }
    ],
    "correctAnswer": "b",
    "explanation": "",
    "category": "General Information",
    "difficulty": "medium",
    "language": "en"
  },
  {
    "id": "gi_new_028",
    "text": "The 1987 Philippine Constitution mandates the State to:",
    "options": [
      {
        "id": "a",
        "text": "protect and conserve the environment."
      },
      {
        "id": "b",
        "text": "promote sustainable development."
      },
      {
        "id": "c",
        "text": "both protect and conserve the environment and promote sustainable development."
      },
      {
        "id": "d",
        "text": "neither protect and conserve the environment nor promote sustainable development."
      }
    ],
    "correctAnswer": "c",
    "explanation": "",
    "category": "General Information",
    "difficulty": "medium",
    "language": "en"
  },
  {
    "id": "gi_new_029",
    "text": "The DENR is the lead agency responsible for:",
    "options": [
      {
        "id": "a",
        "text": "environmental management and protection."
      },
      {
        "id": "b",
        "text": "natural resources management."
      },
      {
        "id": "c",
        "text": "both environmental management and protection and natural resources management."
      },
      {
        "id": "d",
        "text": "neither of the above."
      }
    ],
    "correctAnswer": "c",
    "explanation": "",
    "category": "General Information",
    "difficulty": "medium",
    "language": "en"
  },
  {
    "id": "gi_new_030",
    "text": "The Clean Air Act of 1999 prohibits the:",
    "options": [
      {
        "id": "a",
        "text": "emission of pollutants into the air."
      },
      {
        "id": "b",
        "text": "burning of garbage."
      },
      {
        "id": "c",
        "text": "use of lead-based paints."
      },
      {
        "id": "d",
        "text": "all of the above."
      }
    ],
    "correctAnswer": "d",
    "explanation": "",
    "category": "General Information",
    "difficulty": "medium",
    "language": "en"
  },
  {
    "id": "gi_new_031",
    "text": "The Clean Water Act of 2004 prohibits the:",
    "options": [
      {
        "id": "a",
        "text": "discharge of pollutants into water bodies."
      },
      {
        "id": "b",
        "text": "dumping of garbage in rivers and streams."
      },
      {
        "id": "c",
        "text": "use of pesticides and fertilizers."
      },
      {
        "id": "d",
        "text": "all of the above."
      }
    ],
    "correctAnswer": "d",
    "explanation": "",
    "category": "General Information",
    "difficulty": "medium",
    "language": "en"
  },
  {
    "id": "gi_new_032",
    "text": "The Solid Waste Management Act of 2000 requires the:",
    "options": [
      {
        "id": "a",
        "text": "segregation of solid waste at the source."
      },
      {
        "id": "b",
        "text": "composting of organic waste."
      },
      {
        "id": "c",
        "text": "recycling of recyclable materials."
      },
      {
        "id": "d",
        "text": "all of the above."
      }
    ],
    "correctAnswer": "d",
    "explanation": "",
    "category": "General Information",
    "difficulty": "medium",
    "language": "en"
  },
  {
    "id": "gi_new_033",
    "text": "The National Greening Program is a program of the DENR to:",
    "options": [
      {
        "id": "a",
        "text": "plant trees."
      },
      {
        "id": "b",
        "text": "conserve forests."
      },
      {
        "id": "c",
        "text": "both plant trees and conserve forests."
      },
      {
        "id": "d",
        "text": "neither plant trees nor conserve forests."
      }
    ],
    "correctAnswer": "c",
    "explanation": "",
    "category": "General Information",
    "difficulty": "medium",
    "language": "en"
  },
  {
    "id": "gi_new_034",
    "text": "Which is NOT a prohibited act under the Philippine Clean Air Act?",
    "options": [
      {
        "id": "a",
        "text": "Operating facilities that discharge regulated water pollutants without required permits"
      },
      {
        "id": "b",
        "text": "Discharging water pollutants into the water body"
      },
      {
        "id": "c",
        "text": "Discharging anything that would pollute groundwater"
      },
      {
        "id": "d",
        "text": "Using leaded gasoline"
      }
    ],
    "correctAnswer": "a",
    "explanation": "Option a is under the Clean Water Act, not Clean Air Act",
    "category": "General Information",
    "difficulty": "medium",
    "language": "en"
  },
  {
    "id": "gi_new_035",
    "text": "Which is NOT a prohibited act under the Philippine Clean Water Act?",
    "options": [
      {
        "id": "a",
        "text": "Disposal of potentially infectious medical waste into sea by vessels"
      },
      {
        "id": "b",
        "text": "Unauthorized transport or dumping of sewage sludge into waters"
      },
      {
        "id": "c",
        "text": "Discharge of oil and harmful substances into inland and territorial waters"
      },
      {
        "id": "d",
        "text": "Construction of dams without required environmental impact assessment"
      }
    ],
    "correctAnswer": "d",
    "explanation": "",
    "category": "General Information",
    "difficulty": "medium",
    "language": "en"
  },
  {
    "id": "gi_new_036",
    "text": "What does the Pollution Control Law (P.D. 1181) primarily focus on?",
    "options": [
      {
        "id": "a",
        "text": "Controlling marine pollution"
      },
      {
        "id": "b",
        "text": "Preventing deforestation"
      },
      {
        "id": "c",
        "text": "Reducing vehicular pollution"
      },
      {
        "id": "d",
        "text": "Regulating industrial waste"
      }
    ],
    "correctAnswer": "c",
    "explanation": "",
    "category": "General Information",
    "difficulty": "medium",
    "language": "en"
  },
  {
    "id": "gi_new_037",
    "text": "The Ecological Solid Waste Management Act of 2000 focuses on:",
    "options": [
      {
        "id": "a",
        "text": "Managing hazardous waste"
      },
      {
        "id": "b",
        "text": "Promoting renewable energy"
      },
      {
        "id": "c",
        "text": "Proper solid waste management"
      },
      {
        "id": "d",
        "text": "Protecting coastal areas"
      }
    ],
    "correctAnswer": "c",
    "explanation": "",
    "category": "General Information",
    "difficulty": "medium",
    "language": "en"
  },
  {
    "id": "gi_new_038",
    "text": "Republic Act 6969 primarily aims to:",
    "options": [
      {
        "id": "a",
        "text": "Promote chemical research and study"
      },
      {
        "id": "b",
        "text": "Control and restrict chemical imports"
      },
      {
        "id": "c",
        "text": "Ensure safe disposal of nuclear waste"
      },
      {
        "id": "d",
        "text": "Regulate the sale of toxic chemicals"
      }
    ],
    "correctAnswer": "b",
    "explanation": "DENR authority to control, restrict, or forbid importation/production/use of hazardous chemicals",
    "category": "General Information",
    "difficulty": "medium",
    "language": "en"
  },
  {
    "id": "gi_new_039",
    "text": "The Food Security Act of 1985 primarily concerns itself with:",
    "options": [
      {
        "id": "a",
        "text": "Protecting endangered species"
      },
      {
        "id": "b",
        "text": "Promoting urbanization"
      },
      {
        "id": "c",
        "text": "Preserving wetlands and soil conservation"
      },
      {
        "id": "d",
        "text": "Managing fisheries"
      }
    ],
    "correctAnswer": "c",
    "explanation": "",
    "category": "General Information",
    "difficulty": "medium",
    "language": "en"
  },
  {
    "id": "gi_new_040",
    "text": "Republic Act 9512 focuses on:",
    "options": [
      {
        "id": "a",
        "text": "Promoting environmental awareness through education"
      },
      {
        "id": "b",
        "text": "Banning environmental organizations"
      },
      {
        "id": "c",
        "text": "Reducing government funding for environmental programs"
      },
      {
        "id": "d",
        "text": "Exploiting natural resources"
      }
    ],
    "correctAnswer": "a",
    "explanation": "",
    "category": "General Information",
    "difficulty": "medium",
    "language": "en"
  },
  {
    "id": "gi_new_041",
    "text": "Which is NOT one of the priority programs of the DENR?",
    "options": [
      {
        "id": "a",
        "text": "Geo-Hazard and Groundwater Assessment"
      },
      {
        "id": "b",
        "text": "Enhanced National Greening Program"
      },
      {
        "id": "c",
        "text": "Intensified Environmental Destruction"
      },
      {
        "id": "d",
        "text": "Intensified Forest Protection and Anti-Illegal Logging"
      }
    ],
    "correctAnswer": "c",
    "explanation": "",
    "category": "General Information",
    "difficulty": "medium",
    "language": "en"
  },
  {
    "id": "gi_new_042",
    "text": "What is the main objective of the Enhanced National Greening Program?",
    "options": [
      {
        "id": "a",
        "text": "Promoting deforestation"
      },
      {
        "id": "b",
        "text": "Reducing the number of trees in the Philippines"
      },
      {
        "id": "c",
        "text": "Planting trees and protecting existing forests"
      },
      {
        "id": "d",
        "text": "Encouraging illegal logging"
      }
    ],
    "correctAnswer": "c",
    "explanation": "",
    "category": "General Information",
    "difficulty": "medium",
    "language": "en"
  },
  {
    "id": "gi_new_043",
    "text": "The Clean Air Program is divided into three sub-programs. Which is NOT one of them?",
    "options": [
      {
        "id": "a",
        "text": "Motor Vehicle Emission Management Program"
      },
      {
        "id": "b",
        "text": "Industrial Emission Management Program"
      },
      {
        "id": "c",
        "text": "Roadside ambient and general ambient air monitoring"
      },
      {
        "id": "d",
        "text": "Clean Water Management Program"
      }
    ],
    "correctAnswer": "d",
    "explanation": "",
    "category": "General Information",
    "difficulty": "medium",
    "language": "en"
  },
  {
    "id": "gi_new_044",
    "text": "The manager caught the newly-hired employee laughing while cry.",
    "options": [
      {
        "id": "a",
        "text": "catch the new hired employee laughing while cry."
      },
      {
        "id": "b",
        "text": "catch the new hired employee laughing and cry."
      },
      {
        "id": "c",
        "text": "caught the newly-hired employee laughing while crying."
      },
      {
        "id": "d",
        "text": "caught the newly-hired employee laughing and cringing."
      }
    ],
    "correctAnswer": "c",
    "explanation": "",
    "category": "General Information",
    "difficulty": "medium",
    "language": "en"
  },
  {
    "id": "gi_new_045",
    "text": "Choose the best sentence:",
    "options": [
      {
        "id": "a",
        "text": "One day, I'll move out and chase my dreams."
      },
      {
        "id": "b",
        "text": "One day, I'll become my dreams chase."
      },
      {
        "id": "c",
        "text": "One day, my dreams will chase me and I'll move out."
      },
      {
        "id": "d",
        "text": "One day, my chase will be dreams."
      }
    ],
    "correctAnswer": "a",
    "explanation": "",
    "category": "General Information",
    "difficulty": "medium",
    "language": "en"
  },
  {
    "id": "gi_new_046",
    "text": "I am anonymous in our town in the sense that nobody knows me.",
    "options": [
      {
        "id": "a",
        "text": "I am unanimous on our town"
      },
      {
        "id": "b",
        "text": "I am unanimous in our town"
      },
      {
        "id": "c",
        "text": "I am anonymous on our town"
      },
      {
        "id": "d",
        "text": "I am Anonymous in our Town"
      }
    ],
    "correctAnswer": "e",
    "explanation": "",
    "category": "General Information",
    "difficulty": "medium",
    "language": "en"
  },
  {
    "id": "gi_new_047",
    "text": "Let the records shows that I swear to tell nothing but the truth.",
    "options": [
      {
        "id": "a",
        "text": "Let the record show that I swore to tell nothing."
      },
      {
        "id": "b",
        "text": "Let the records show that I swear to tell nothing but the truth."
      },
      {
        "id": "c",
        "text": "Let the record shows that I swore to tell nothing."
      },
      {
        "id": "d",
        "text": "Let the records shows that I swear to tell nothing but the truth."
      }
    ],
    "correctAnswer": "b",
    "explanation": "",
    "category": "General Information",
    "difficulty": "medium",
    "language": "en"
  },
  {
    "id": "gi_new_048",
    "text": "That is the lie that started all the trouble in your life!",
    "options": [
      {
        "id": "a",
        "text": "the lay that started all the troubles"
      },
      {
        "id": "b",
        "text": "the lie that started all the troubles"
      },
      {
        "id": "c",
        "text": "the lay that start trouble"
      },
      {
        "id": "d",
        "text": "the lie that start troubles"
      }
    ],
    "correctAnswer": "e",
    "explanation": "",
    "category": "General Information",
    "difficulty": "medium",
    "language": "en"
  },
  {
    "id": "gi_new_049",
    "text": "a. \"I should have killed you when I had the chance!\" the man said.",
    "options": [
      {
        "id": "a",
        "text": "I should have killed you when I had the chance. The man said."
      },
      {
        "id": "b",
        "text": "I should have killed you when I had the chance, the man said."
      },
      {
        "id": "c",
        "text": "I should had killed you when I have the chance. The Man said."
      },
      {
        "id": "d",
        "text": "I should had killed you when I have the chance, the Man said."
      }
    ],
    "correctAnswer": "e",
    "explanation": "",
    "category": "General Information",
    "difficulty": "medium",
    "language": "en"
  },
  {
    "id": "gi_new_050",
    "text": "The student who's car is parked in front of the gate is really pretty.",
    "options": [
      {
        "id": "a",
        "text": "The student, whose car is parked in front of the gate, is really pretty."
      },
      {
        "id": "b",
        "text": "The student's car parked in front of the gate is really pretty."
      },
      {
        "id": "c",
        "text": "The student, who's car is parked in front of the gate, is really pretty."
      },
      {
        "id": "d",
        "text": "The student is a pretty car parked in front of the gate."
      }
    ],
    "correctAnswer": "a",
    "explanation": "whose = possessive; who's = who is",
    "category": "General Information",
    "difficulty": "medium",
    "language": "en"
  },
  {
    "id": "gi_new_051",
    "text": "Choose the best sentence:",
    "options": [
      {
        "id": "a",
        "text": "Their car was parked there."
      },
      {
        "id": "b",
        "text": "Their car was parked their."
      },
      {
        "id": "c",
        "text": "There car was parked there."
      },
      {
        "id": "d",
        "text": "There car was parked their."
      }
    ],
    "correctAnswer": "a",
    "explanation": "",
    "category": "General Information",
    "difficulty": "medium",
    "language": "en"
  },
  {
    "id": "gi_new_052",
    "text": "Solomon taught his sister how to play the guitar.",
    "options": [
      {
        "id": "a",
        "text": "Solomon learn his sister how to play the guitar."
      },
      {
        "id": "b",
        "text": "Solomon learned his sister how to play the guitar."
      },
      {
        "id": "c",
        "text": "Solomon teach his sister how to play the guitar."
      },
      {
        "id": "d",
        "text": "Solomon teached his sister how to play the guitar."
      }
    ],
    "correctAnswer": "e",
    "explanation": "",
    "category": "General Information",
    "difficulty": "medium",
    "language": "en"
  },
  {
    "id": "gi_new_053",
    "text": "Choose the best sentence:",
    "options": [
      {
        "id": "a",
        "text": "Juliette finished this project fast than the other."
      },
      {
        "id": "b",
        "text": "Juliette finished this project faster than the other."
      },
      {
        "id": "c",
        "text": "Juliette finished this project fastest than the other."
      },
      {
        "id": "d",
        "text": "Juliette finished these project fast than the others."
      }
    ],
    "correctAnswer": "b",
    "explanation": "",
    "category": "General Information",
    "difficulty": "medium",
    "language": "en"
  }
]